arcane/tiktok/__init__.py
arcane/tiktok/const.py
arcane/tiktok/exceptions.py
arcane/tiktok/lib.py
arcane/tiktok/tiktok.py
arcane_tiktok-0.1.7.dist-info/METADATA
arcane_tiktok-0.1.7.dist-info/WHEEL
arcane_tiktok-0.1.7.dist-info/RECORD
